LICENSE.txt
README.txt
setup.py
NEW_BMI_IJ.egg-info/PKG-INFO
NEW_BMI_IJ.egg-info/SOURCES.txt
NEW_BMI_IJ.egg-info/dependency_links.txt
NEW_BMI_IJ.egg-info/top_level.txt
init/__init__.py