Metadata-Version: 2.1
Name: NEW-BMI-IJ
Version: 0.0.1
Summary: basic BMI Calculator
Home-page: UNKNOWN
Author: Irakli Jorbenadze
Author-email: irakli.jorbenadze@gmail.com
License: MIT
Keywords: BMI_NEW
Platform: UNKNOWN
Classifier: Development Status :: 5 - Production/Stable
Classifier: Intended Audience :: Education
Classifier: Operating System :: Microsoft :: Windows :: Windows 10
Classifier: License :: OSI Approved :: MIT License
Classifier: Programming Language :: Python :: 3
License-File: LICENSE.txt
